vs_server_colab/__init__.py
vs_server_colab/cli.py
vs_server_colab/core.py
vs_server_colab/src/ngrok.sh
vs_server_colab/src/vs_server.sh
vs_server_colab-1.1.3.dist-info/METADATA
vs_server_colab-1.1.3.dist-info/WHEEL
vs_server_colab-1.1.3.dist-info/entry_points.txt
vs_server_colab-1.1.3.dist-info/licenses/LICENSE
vs_server_colab-1.1.3.dist-info/RECORD
