Metadata-Version: 2.4
Name: vs-server-colab
Version: 1.1.3
Summary: Expose a code-server instance over ngrok
Project-URL: Homepage, https://github.com/hasinthaka/vs-server-script
Author: Hasinthaka
License: MIT License
License-File: LICENSE
Keywords: code-server,colab,ngrok,vs-code
Classifier: License :: OSI Approved :: MIT License
Classifier: Operating System :: POSIX :: Linux
Classifier: Programming Language :: Python :: 3
Requires-Python: >=3.6
